pypos/__init__.py
pypos/hmm.py
pypos/tagger.py
pypos-0.1.2.dist-info/LICENSE
pypos-0.1.2.dist-info/METADATA
pypos-0.1.2.dist-info/WHEEL
pypos-0.1.2.dist-info/top_level.txt
pypos-0.1.2.dist-info/RECORD
