Metadata-Version: 2.1
Name: pypos
Version: 0.1.2
Summary: A part of speech tagger based on Hidden Markov models
Home-page: https://github.com/palle-k/pypos
Author: Palle Klewitz
Author-email: palleklewitz@icloud.com
License: UNKNOWN
Platform: UNKNOWN
Classifier: Programming Language :: Python :: 3
Classifier: License :: OSI Approved :: MIT License
Classifier: Operating System :: OS Independent
